mpremote_path/__init__.py
mpremote_path/_version.py
mpremote_path/board.py
mpremote_path/mpremote_path.py
mpremote_path/py.typed
mpremote_path/util/__init__.py
mpremote_path/util/mpfs.py
mpremote_path/util/mpfsops.py
mpremote_path-0.1.8.dist-info/METADATA
mpremote_path-0.1.8.dist-info/WHEEL
mpremote_path-0.1.8.dist-info/entry_points.txt
mpremote_path-0.1.8.dist-info/licenses/LICENSE
mpremote_path-0.1.8.dist-info/RECORD
