Metadata-Version: 2.4
Name: mpremote-path
Version: 0.1.8
Summary: Pathlib compatible interface to files on a MicroPython device
Project-URL: Homepage, https://github.com/glenn20/mpremote-path
Author-email: glenn20 <6965319+glenn20@users.noreply.github.com>
License: MIT
License-File: LICENSE
Classifier: Intended Audience :: Developers
Classifier: License :: OSI Approved :: MIT License
Classifier: Operating System :: OS Independent
Classifier: Programming Language :: Python :: 3
Classifier: Programming Language :: Python :: 3.8
Classifier: Programming Language :: Python :: 3.9
Classifier: Programming Language :: Python :: 3.10
Classifier: Programming Language :: Python :: 3.11
Classifier: Programming Language :: Python :: 3.12
Classifier: Programming Language :: Python :: 3.13
Classifier: Topic :: Software Development :: Embedded Systems
Classifier: Topic :: Software Development :: Libraries
Classifier: Typing :: Typed
Requires-Python: >=3.9
Requires-Dist: mpremote!=1.24.0,>=1.20
